<annotation><folder>OAK2017</folder><filename>scene_varied_43.png</filename><source><database>The OAK2017 Database</database><annotation>ERIK OAK2017</annotation></source><owner>Erik Ryden</owner><size><width>960</width><height>540</height><depth>3</depth></size><segmented>0</segmented><object><name>apple</name><pose>left</pose><truncated>1</truncated><difficult>0</difficult><bndbox><xmin>757</xmin><ymin>392</ymin><xmax>960</xmax><ymax>526</ymax></bndbox></object><object><name>banana</name><pose>left</pose><truncated>1</truncated><difficult>0</difficult><bndbox><xmin>1</xmin><ymin>242</ymin><xmax>270</xmax><ymax>348</ymax></bndbox></object><object><name>orange</name><pose>left</pose><truncated>1</truncated><difficult>0</difficult><bndbox><xmin>528</xmin><ymin>124</ymin><xmax>588</xmax><ymax>179</ymax></bndbox></object><object><name>orange</name><pose>left</pose><truncated>1</truncated><difficult>0</difficult><bndbox><xmin>288</xmin><ymin>296</ymin><xmax>460</xmax><ymax>439</ymax></bndbox></object><object><name>cola_can</name><pose>left</pose><truncated>1</truncated><difficult>0</difficult><bndbox><xmin>951</xmin><ymin>132</ymin><xmax>960</xmax><ymax>207</ymax></bndbox></object><object><name>apple</name><pose>left</pose><truncated>1</truncated><difficult>0</difficult><bndbox><xmin>418</xmin><ymin>409</ymin><xmax>711</xmax><ymax>540</ymax></bndbox></object><object><name>banana</name><pose>left</pose><truncated>1</truncated><difficult>0</difficult><bndbox><xmin>1</xmin><ymin>226</ymin><xmax>27</xmax><ymax>251</ymax></bndbox></object><object><name>orange</name><pose>left</pose><truncated>1</truncated><difficult>0</difficult><bndbox><xmin>868</xmin><ymin>473</ymin><xmax>960</xmax><ymax>540</ymax></bndbox></object></annotation>